{"contentDataResult":{"createdDate":"2024-02-12T16:49:15Z"},"modifiedDate":"2024-02-12T17:17:08Z","modelEntity":{"experimentID":"C2B66F90-7375-40D6-BBAB-CF220D20B269","id":"958F12C9-7E50-40A1-9DC2-C58C9B716200","preferredFilename":"","title":"","modifiedDate":"2024-02-12T16:49:15Z","version":"1.0","createdDate":"2024-02-12T16:49:15Z","modelURL":"Models\/Image%20Classification%20%2010.mlmodel"},"activityEntities":["trainingDataAdded",[{"title":"Training Data Added","id":"E494AD30-1B17-4C65-813E-2489F665176B","subtitle":"01 datasets basic","event":"trainingDataAdded","createdDate":"2024-02-12T16:50:17Z"}],"trainingStarted",[{"id":"47E758E1-53FF-460C-935E-8E8403E4471D","createdDate":"2024-02-12T16:50:25Z","subtitle":"25 iterations","title":"Training Started","event":"trainingStarted"}],"trainingFinished",[{"title":"Training Completed","id":"7BB554C5-8BFA-40A3-B51A-C64FBB748C7A","event":"trainingFinished","subtitle":"Model converged at 26 iterations","createdDate":"2024-02-12T16:51:33Z"}],"experimentCreated",[{"title":"Model Source Created","event":"experimentCreated","id":"EBF23201-5CB9-4548-85B9-764532F3F04D","subtitle":"Image Classification  10","createdDate":"2024-02-12T16:49:15Z"}],"trainingExtended",[{"title":"Training Extended","event":"trainingExtended","subtitle":"20 more iterations","id":"36F591F7-1733-49D0-8A5D-F2D846BC2FFC","createdDate":"2024-02-12T16:50:52Z"},{"id":"813A220C-952C-43B7-832B-1D72612675C5","subtitle":"20 more iterations","event":"trainingExtended","title":"Training Extended","createdDate":"2024-02-12T16:51:02Z"},{"createdDate":"2024-02-12T16:51:22Z","event":"trainingExtended","id":"EFDECEA6-E934-4063-80AE-532034A31467","subtitle":"20 more iterations","title":"Training Extended"},{"title":"Training Extended","event":"trainingExtended","subtitle":"20 more iterations","createdDate":"2024-02-12T16:51:27Z","id":"A794B2FD-4A88-4569-B98F-CBAEB62B9858"},{"title":"Training Extended","id":"F9AE185C-40A1-4509-8DA1-7053D8611C0B","subtitle":"20 more iterations","createdDate":"2024-02-12T16:51:32Z","event":"trainingExtended"}],"snapshotCreated",[{"id":"9C3700FE-5139-4094-AB44-770E5DB33E83","title":"Snapshot Saved","event":"snapshotCreated","createdDate":"2024-02-12T16:50:52Z","subtitle":"Snapshot created at iteration 25"},{"subtitle":"Snapshot created at iteration 50","title":"Snapshot Saved","id":"A6C3A854-4353-44B9-B125-7F7EACA30ECD","createdDate":"2024-02-12T16:51:01Z","event":"snapshotCreated"},{"createdDate":"2024-02-12T16:51:22Z","id":"78D45D2F-B12C-4CC7-8128-5E898B1A6DA1","event":"snapshotCreated","subtitle":"Snapshot created at iteration 75","title":"Snapshot Saved"},{"title":"Snapshot Saved","id":"4292B17C-667B-4F5B-A27F-752BDDC6F6BC","subtitle":"Snapshot created at iteration 100","createdDate":"2024-02-12T16:51:27Z","event":"snapshotCreated"},{"subtitle":"Snapshot created at iteration 125","event":"snapshotCreated","id":"BA8CB67C-6F71-48CD-B2C5-91AFB0228846","createdDate":"2024-02-12T16:51:32Z","title":"Snapshot Saved"}]],"state":"trained","id":"C2B66F90-7375-40D6-BBAB-CF220D20B269","validationEntity":{"analysedDataType":"auto","dataResult":{"createdDate":"2024-02-12T16:49:15Z"}},"snapshotRole":{"withSnapshots":["8053E3A0-A6D3-477C-BD41-38AE4A0C0912","E58C226D-BA70-4AEF-AE95-2A7EF534D9C6","18C24218-1FA0-492A-A4E0-000BDA085CD4","235D8CF7-E6F7-4A38-A30D-57F462B51B99","2514B055-3C8E-428C-8712-A94C449F658F"]},"preferredFilename":"Image Classification  10","evaluationEntity":{"analysedDataType":"none","id":"4a731e44-d27b-4956-9bba-9d2431bfd117","dataResult":{}},"createdDate":"2024-02-12T16:49:15Z","version":"1.0","trainingEntity":{"checkpointMetrics":{"125":{"metrics":{},"createdDate":"2024-02-12T16:51:28Z","iteration":125},"50":{"iteration":50,"createdDate":"2024-02-12T16:50:53Z","metrics":{}},"100":{"metrics":{},"createdDate":"2024-02-12T16:51:23Z","iteration":100},"150":{"createdDate":"2024-02-12T16:51:33Z","iteration":150,"metrics":{}},"25":{"createdDate":"2024-02-12T16:50:40Z","iteration":25,"metrics":{}},"75":{"iteration":75,"createdDate":"2024-02-12T16:51:02Z","metrics":{}}},"startTime":"2024-02-12T16:51:32Z","resumableCheckpointURL":"Checkpoints\/C2B66F90-7375-40D6-BBAB-CF220D20B269.ImageClassification10.checkpoint","dataSourceID":"6A8516B6-CB84-4F90-B064-E335BF7C3621","progress":[{"currentRowIndex":0,"tableDone":false,"tableIndex":0,"isLast":false,"count":0,"percentComplete":0},{"icTrainingColumnHeader":{"elapsedTime":0.07384693622589111,"hasValidation":true,"trainingAccuracy":0.614404432132964,"validationAccuracy":0.6421052631578947,"iterationCount":2},"percentComplete":0,"currentRowIndex":0,"tableDone":false,"isLast":false,"count":2,"tableIndex":1},{"tableDone":false,"count":3,"icTrainingColumnHeader":{"validationAccuracy":0.6631578947368421,"iterationCount":3,"hasValidation":true,"elapsedTime":0.1132129430770874,"trainingAccuracy":0.6786703601108033},"currentRowIndex":0,"tableIndex":0,"percentComplete":0,"isLast":false},{"currentRowIndex":0,"tableIndex":1,"count":4,"tableDone":false,"isLast":false,"percentComplete":0,"icTrainingColumnHeader":{"elapsedTime":0.13171696662902832,"trainingAccuracy":0.7013850415512466,"iterationCount":4,"validationAccuracy":0.6736842105263158,"hasValidation":true}},{"tableDone":false,"percentComplete":0,"isLast":false,"tableIndex":2,"currentRowIndex":0,"icTrainingColumnHeader":{"hasValidation":true,"iterationCount":5,"elapsedTime":0.14987599849700928,"validationAccuracy":0.7157894736842105,"trainingAccuracy":0.7318559556786703},"count":5},{"currentRowIndex":0,"tableDone":false,"percentComplete":0,"isLast":false,"tableIndex":0,"count":10},{"count":11,"icTrainingColumnHeader":{"hasValidation":true,"iterationCount":11,"trainingAccuracy":0.8570637119113573,"validationAccuracy":0.7684210526315789,"elapsedTime":0.26260101795196533},"percentComplete":0,"currentRowIndex":0,"tableIndex":0,"tableDone":false,"isLast":false},{"currentRowIndex":0,"count":15,"percentComplete":0,"isLast":false,"tableIndex":0,"tableDone":false},{"isLast":false,"count":16,"currentRowIndex":0,"percentComplete":0,"tableDone":true,"icTrainingColumnHeader":{"elapsedTime":0.38565194606781006,"hasValidation":true,"trainingAccuracy":0.9085872576177285,"validationAccuracy":0.7894736842105263,"iterationCount":16},"tableIndex":0},{"count":17,"tableIndex":0,"currentRowIndex":0,"percentComplete":0,"tableDone":true,"isLast":false,"icTrainingColumnHeader":{"iterationCount":17,"hasValidation":true,"trainingAccuracy":0.9174515235457064,"elapsedTime":0.3970980644226074,"validationAccuracy":0.8}},{"count":20,"percentComplete":0,"tableIndex":0,"icTrainingColumnHeader":{"trainingAccuracy":0.9357340720221606,"iterationCount":20,"hasValidation":true,"validationAccuracy":0.8,"elapsedTime":0.4519989490509033},"isLast":false,"tableDone":true,"currentRowIndex":0},{"tableIndex":0,"percentComplete":0,"tableDone":false,"currentRowIndex":0,"isLast":false,"icTrainingColumnHeader":{"validationAccuracy":0.8526315789473684,"hasValidation":true,"iterationCount":21,"elapsedTime":0.49508893489837646,"trainingAccuracy":0.9418282548476454},"count":21},{"isLast":false,"count":25,"percentComplete":0,"tableIndex":0,"currentRowIndex":0,"tableDone":false},{"count":26,"isLast":false,"tableIndex":0,"percentComplete":0,"icTrainingColumnHeader":{"elapsedTime":0.6071649789810181,"hasValidation":true,"iterationCount":26,"trainingAccuracy":0.9673130193905817,"validationAccuracy":0.8421052631578947},"tableDone":true,"currentRowIndex":0},{"percentComplete":0,"isLast":false,"tableDone":false,"currentRowIndex":0,"count":30,"tableIndex":0},{"percentComplete":0,"tableIndex":0,"tableDone":false,"currentRowIndex":0,"isLast":false,"count":35},{"percentComplete":0,"isLast":false,"currentRowIndex":0,"count":40,"tableIndex":0,"tableDone":false},{"tableDone":false,"currentRowIndex":0,"isLast":false,"count":45,"percentComplete":0,"tableIndex":0},{"currentRowIndex":0,"tableIndex":0,"isLast":false,"count":50,"tableDone":false,"percentComplete":0},{"tableIndex":0,"tableDone":false,"isLast":false,"currentRowIndex":0,"count":55,"percentComplete":0},{"percentComplete":0,"currentRowIndex":0,"tableDone":false,"isLast":false,"tableIndex":0,"count":60},{"count":65,"percentComplete":0,"currentRowIndex":0,"tableIndex":0,"tableDone":false,"isLast":false},{"count":70,"percentComplete":0,"tableIndex":0,"currentRowIndex":0,"tableDone":false,"isLast":false},{"isLast":false,"percentComplete":0,"tableIndex":0,"tableDone":false,"count":75,"currentRowIndex":0},{"tableIndex":0,"isLast":false,"tableDone":false,"currentRowIndex":0,"count":80,"percentComplete":0},{"tableIndex":0,"currentRowIndex":0,"isLast":false,"tableDone":false,"count":85,"percentComplete":0},{"currentRowIndex":0,"tableIndex":0,"tableDone":false,"isLast":false,"count":90,"percentComplete":0},{"tableDone":false,"count":95,"isLast":false,"currentRowIndex":0,"percentComplete":0,"tableIndex":0},{"tableDone":false,"tableIndex":0,"isLast":false,"count":100,"percentComplete":0,"currentRowIndex":0},{"percentComplete":0,"tableDone":false,"tableIndex":0,"currentRowIndex":0,"isLast":false,"count":105},{"tableDone":false,"tableIndex":0,"isLast":false,"percentComplete":0,"currentRowIndex":0,"count":110},{"isLast":false,"currentRowIndex":0,"tableIndex":0,"tableDone":false,"count":115,"percentComplete":0},{"tableIndex":0,"count":120,"currentRowIndex":0,"tableDone":false,"isLast":false,"percentComplete":0},{"percentComplete":0,"count":125,"tableDone":false,"tableIndex":0,"currentRowIndex":0,"isLast":false},{"count":130,"tableIndex":0,"percentComplete":0,"currentRowIndex":0,"tableDone":false,"isLast":false},{"tableDone":false,"currentRowIndex":0,"count":135,"percentComplete":0,"isLast":false,"tableIndex":0},{"isLast":false,"count":140,"percentComplete":0,"tableIndex":0,"tableDone":false,"currentRowIndex":0},{"count":145,"tableDone":false,"currentRowIndex":0,"percentComplete":0,"isLast":false,"tableIndex":0},{"isLast":false,"tableDone":false,"currentRowIndex":0,"count":150,"percentComplete":0,"tableIndex":0},{"tableDone":false,"tableIndex":0,"isLast":false,"percentComplete":0,"currentRowIndex":0,"count":155},{"tableIndex":0,"currentRowIndex":0,"isLast":false,"count":160,"percentComplete":0,"tableDone":false},{"tableDone":false,"tableIndex":0,"isLast":false,"count":165,"currentRowIndex":0,"percentComplete":0},{"tableDone":false,"currentRowIndex":0,"count":170,"percentComplete":0,"isLast":false,"tableIndex":0},{"isLast":false,"tableIndex":0,"tableDone":false,"currentRowIndex":0,"count":175,"percentComplete":0},{"currentRowIndex":0,"isLast":false,"count":180,"tableIndex":0,"tableDone":false,"percentComplete":0},{"isLast":false,"count":185,"tableIndex":0,"currentRowIndex":0,"tableDone":false,"percentComplete":0},{"percentComplete":0,"tableDone":false,"tableIndex":0,"currentRowIndex":0,"isLast":false,"count":190},{"tableDone":false,"currentRowIndex":0,"count":195,"percentComplete":0,"tableIndex":0,"isLast":false},{"isLast":false,"currentRowIndex":0,"tableDone":false,"tableIndex":0,"count":200,"percentComplete":0},{"isLast":false,"tableIndex":0,"currentRowIndex":0,"count":205,"tableDone":false,"percentComplete":0},{"isLast":false,"count":210,"percentComplete":0,"tableDone":false,"tableIndex":0,"currentRowIndex":0},{"currentRowIndex":0,"tableIndex":0,"isLast":false,"tableDone":false,"count":215,"percentComplete":0},{"isLast":false,"count":220,"tableDone":false,"currentRowIndex":0,"percentComplete":0,"tableIndex":0},{"tableIndex":0,"count":225,"currentRowIndex":0,"percentComplete":0,"tableDone":false,"isLast":false},{"tableDone":false,"currentRowIndex":0,"isLast":false,"tableIndex":0,"count":230,"percentComplete":0},{"count":235,"percentComplete":0,"tableIndex":0,"tableDone":false,"currentRowIndex":0,"isLast":false},{"percentComplete":0,"count":240,"isLast":false,"tableDone":false,"tableIndex":0,"currentRowIndex":0},{"isLast":false,"tableIndex":0,"count":245,"percentComplete":0,"tableDone":false,"currentRowIndex":0},{"count":250,"percentComplete":0,"tableIndex":0,"isLast":false,"tableDone":false,"currentRowIndex":0},{"currentRowIndex":0,"tableIndex":0,"tableDone":false,"percentComplete":0,"count":255,"isLast":false},{"isLast":false,"tableIndex":0,"percentComplete":0,"count":260,"tableDone":false,"currentRowIndex":0},{"count":265,"percentComplete":0,"tableDone":false,"currentRowIndex":0,"tableIndex":0,"isLast":false},{"tableDone":false,"count":270,"percentComplete":0,"tableIndex":0,"isLast":false,"currentRowIndex":0},{"currentRowIndex":0,"count":275,"tableDone":false,"isLast":false,"tableIndex":0,"percentComplete":0},{"tableIndex":0,"currentRowIndex":0,"isLast":false,"percentComplete":0,"count":280,"tableDone":false},{"count":285,"tableDone":false,"tableIndex":0,"isLast":false,"currentRowIndex":0,"percentComplete":0},{"percentComplete":0,"currentRowIndex":0,"tableIndex":0,"tableDone":false,"isLast":false,"count":290},{"tableDone":false,"count":295,"tableIndex":0,"isLast":false,"percentComplete":0,"currentRowIndex":0},{"isLast":false,"percentComplete":0,"tableIndex":0,"tableDone":false,"count":300,"currentRowIndex":0},{"tableDone":false,"count":305,"tableIndex":0,"currentRowIndex":0,"isLast":false,"percentComplete":0},{"count":310,"currentRowIndex":0,"percentComplete":0,"tableIndex":0,"tableDone":false,"isLast":false},{"isLast":false,"currentRowIndex":0,"count":315,"percentComplete":0,"tableIndex":0,"tableDone":false},{"tableDone":false,"currentRowIndex":0,"isLast":false,"tableIndex":0,"count":320,"percentComplete":0},{"currentRowIndex":0,"percentComplete":0,"isLast":false,"tableIndex":0,"tableDone":false,"count":325},{"count":330,"isLast":false,"tableIndex":0,"currentRowIndex":0,"tableDone":false,"percentComplete":0},{"isLast":false,"count":335,"tableDone":false,"percentComplete":0,"tableIndex":0,"currentRowIndex":0},{"count":340,"percentComplete":0,"tableDone":false,"currentRowIndex":0,"isLast":false,"tableIndex":0},{"currentRowIndex":0,"tableIndex":0,"count":345,"tableDone":false,"percentComplete":0,"isLast":false},{"isLast":false,"percentComplete":0,"currentRowIndex":0,"count":350,"tableDone":false,"tableIndex":0},{"tableDone":false,"percentComplete":0,"tableIndex":0,"currentRowIndex":0,"isLast":false,"count":355},{"isLast":false,"currentRowIndex":0,"count":360,"tableDone":false,"tableIndex":0,"percentComplete":0},{"isLast":false,"count":365,"percentComplete":0,"tableDone":false,"currentRowIndex":0,"tableIndex":0},{"currentRowIndex":0,"isLast":false,"tableIndex":0,"count":370,"percentComplete":0,"tableDone":false},{"isLast":false,"tableIndex":0,"currentRowIndex":0,"count":375,"percentComplete":0,"tableDone":false},{"percentComplete":0,"count":380,"tableIndex":0,"currentRowIndex":0,"tableDone":false,"isLast":false},{"isLast":false,"tableDone":false,"currentRowIndex":0,"count":385,"percentComplete":0,"tableIndex":0},{"tableIndex":0,"tableDone":false,"count":390,"currentRowIndex":0,"isLast":false,"percentComplete":0},{"currentRowIndex":0,"count":395,"isLast":false,"tableIndex":0,"percentComplete":0,"tableDone":false},{"percentComplete":0,"currentRowIndex":0,"tableDone":false,"isLast":false,"count":400,"tableIndex":0},{"count":405,"tableIndex":0,"currentRowIndex":0,"tableDone":false,"isLast":false,"percentComplete":0},{"tableDone":false,"percentComplete":0,"currentRowIndex":0,"tableIndex":0,"isLast":false,"count":410},{"count":415,"tableIndex":0,"percentComplete":0,"currentRowIndex":0,"tableDone":false,"isLast":false},{"tableDone":false,"currentRowIndex":0,"percentComplete":0,"isLast":false,"count":420,"tableIndex":0},{"percentComplete":0,"currentRowIndex":0,"count":425,"tableIndex":0,"tableDone":false,"isLast":false},{"tableIndex":0,"tableDone":false,"currentRowIndex":0,"isLast":false,"count":430,"percentComplete":0},{"tableIndex":0,"isLast":false,"currentRowIndex":0,"count":435,"percentComplete":0,"tableDone":false},{"tableIndex":0,"isLast":false,"count":440,"percentComplete":0,"currentRowIndex":0,"tableDone":false},{"tableIndex":0,"tableDone":false,"currentRowIndex":0,"isLast":false,"percentComplete":0,"count":445},{"percentComplete":0,"tableIndex":0,"isLast":false,"tableDone":false,"count":450,"currentRowIndex":0},{"count":455,"currentRowIndex":0,"isLast":false,"tableDone":false,"percentComplete":0,"tableIndex":0},{"tableIndex":0,"isLast":false,"tableDone":false,"percentComplete":0,"count":460,"currentRowIndex":0},{"tableIndex":0,"count":465,"percentComplete":0,"tableDone":false,"currentRowIndex":0,"isLast":false},{"isLast":false,"currentRowIndex":0,"percentComplete":0,"tableDone":false,"count":470,"tableIndex":0},{"count":475,"percentComplete":0,"tableIndex":0,"isLast":false,"tableDone":false,"currentRowIndex":0},{"tableIndex":0,"currentRowIndex":0,"count":480,"isLast":false,"percentComplete":0,"tableDone":false},{"currentRowIndex":0,"percentComplete":0,"tableDone":false,"isLast":false,"tableIndex":0,"count":485},{"count":490,"isLast":false,"percentComplete":0,"tableDone":false,"currentRowIndex":0,"tableIndex":0},{"tableIndex":0,"isLast":false,"currentRowIndex":0,"tableDone":false,"count":495,"percentComplete":0},{"percentComplete":0,"tableDone":false,"currentRowIndex":0,"isLast":false,"tableIndex":0,"count":500},{"tableIndex":0,"currentRowIndex":0,"tableDone":false,"count":505,"percentComplete":0,"isLast":false},{"tableDone":false,"percentComplete":0,"currentRowIndex":0,"isLast":false,"count":510,"tableIndex":0},{"isLast":false,"tableIndex":0,"percentComplete":0,"tableDone":false,"currentRowIndex":0,"count":515},{"currentRowIndex":0,"isLast":false,"tableIndex":0,"tableDone":false,"percentComplete":0,"count":520},{"count":525,"tableIndex":0,"currentRowIndex":0,"isLast":false,"percentComplete":0,"tableDone":false},{"currentRowIndex":0,"count":530,"tableIndex":0,"tableDone":false,"isLast":false,"percentComplete":0},{"percentComplete":0,"currentRowIndex":0,"count":535,"tableIndex":0,"tableDone":false,"isLast":false},{"tableIndex":0,"tableDone":false,"count":540,"percentComplete":0,"currentRowIndex":0,"isLast":false},{"isLast":false,"currentRowIndex":0,"tableIndex":0,"tableDone":false,"count":545,"percentComplete":0},{"percentComplete":0,"tableDone":false,"count":550,"currentRowIndex":0,"isLast":false,"tableIndex":0},{"count":555,"percentComplete":0,"tableIndex":0,"tableDone":false,"currentRowIndex":0,"isLast":false},{"tableIndex":0,"isLast":false,"tableDone":false,"percentComplete":0,"count":560,"currentRowIndex":0},{"tableIndex":0,"tableDone":false,"isLast":false,"percentComplete":0,"count":565,"currentRowIndex":0},{"percentComplete":0,"count":570,"isLast":false,"currentRowIndex":0,"tableDone":false,"tableIndex":0},{"tableDone":false,"currentRowIndex":0,"percentComplete":0,"isLast":false,"count":575,"tableIndex":0},{"tableDone":false,"count":580,"percentComplete":0,"isLast":false,"currentRowIndex":0,"tableIndex":0},{"isLast":false,"count":585,"percentComplete":0,"currentRowIndex":0,"tableDone":false,"tableIndex":0},{"tableIndex":0,"tableDone":false,"currentRowIndex":0,"percentComplete":0,"isLast":false,"count":590},{"isLast":false,"percentComplete":0,"count":595,"tableDone":false,"tableIndex":0,"currentRowIndex":0},{"currentRowIndex":0,"tableDone":false,"tableIndex":0,"count":600,"percentComplete":0,"isLast":false},{"tableIndex":0,"currentRowIndex":0,"percentComplete":0,"tableDone":false,"isLast":false,"count":605},{"isLast":false,"percentComplete":0,"tableIndex":0,"tableDone":false,"count":610,"currentRowIndex":0},{"percentComplete":0,"tableDone":false,"tableIndex":0,"currentRowIndex":0,"count":615,"isLast":false},{"tableDone":false,"isLast":false,"count":620,"percentComplete":0,"tableIndex":0,"currentRowIndex":0},{"tableIndex":0,"count":625,"percentComplete":0,"isLast":false,"tableDone":false,"currentRowIndex":0},{"tableIndex":0,"percentComplete":0,"tableDone":false,"currentRowIndex":0,"isLast":false,"count":630},{"currentRowIndex":0,"tableIndex":0,"tableDone":false,"isLast":false,"count":635,"percentComplete":0},{"percentComplete":0,"count":640,"isLast":false,"tableDone":false,"currentRowIndex":0,"tableIndex":0},{"tableIndex":0,"currentRowIndex":0,"isLast":false,"percentComplete":0,"count":645,"tableDone":false},{"isLast":false,"count":650,"percentComplete":0,"tableDone":false,"tableIndex":0,"currentRowIndex":0},{"isLast":false,"percentComplete":0,"tableDone":false,"tableIndex":0,"currentRowIndex":0,"count":655},{"count":660,"percentComplete":0,"currentRowIndex":0,"tableIndex":0,"tableDone":false,"isLast":false},{"currentRowIndex":0,"count":665,"tableIndex":0,"tableDone":false,"isLast":false,"percentComplete":0},{"percentComplete":0,"tableDone":false,"isLast":false,"tableIndex":0,"currentRowIndex":0,"count":670},{"percentComplete":0,"currentRowIndex":0,"tableDone":false,"tableIndex":0,"isLast":false,"count":675},{"count":680,"percentComplete":0,"tableDone":false,"currentRowIndex":0,"tableIndex":0,"isLast":false},{"isLast":false,"tableIndex":0,"tableDone":false,"currentRowIndex":0,"percentComplete":0,"count":685},{"isLast":false,"count":690,"currentRowIndex":0,"tableIndex":0,"percentComplete":0,"tableDone":false},{"tableIndex":0,"percentComplete":0,"currentRowIndex":0,"tableDone":false,"isLast":false,"count":695},{"currentRowIndex":0,"tableDone":false,"count":700,"isLast":false,"percentComplete":0,"tableIndex":0},{"count":705,"tableIndex":0,"tableDone":false,"currentRowIndex":0,"isLast":false,"percentComplete":0},{"currentRowIndex":0,"isLast":false,"count":710,"tableIndex":0,"percentComplete":0,"tableDone":false},{"percentComplete":0,"count":715,"tableDone":false,"currentRowIndex":0,"tableIndex":0,"isLast":false},{"percentComplete":0,"isLast":false,"count":720,"tableDone":false,"tableIndex":0,"currentRowIndex":0},{"percentComplete":0,"isLast":false,"tableDone":false,"count":725,"tableIndex":0,"currentRowIndex":0},{"tableDone":false,"count":730,"isLast":false,"tableIndex":0,"percentComplete":0,"currentRowIndex":0},{"count":735,"percentComplete":0,"tableIndex":0,"tableDone":false,"currentRowIndex":0,"isLast":false},{"count":740,"tableIndex":0,"isLast":false,"currentRowIndex":0,"percentComplete":0,"tableDone":false},{"isLast":false,"tableIndex":0,"tableDone":false,"count":745,"percentComplete":0,"currentRowIndex":0},{"count":750,"isLast":false,"currentRowIndex":0,"percentComplete":0,"tableIndex":0,"tableDone":false},{"currentRowIndex":0,"tableIndex":0,"tableDone":false,"percentComplete":0,"count":755,"isLast":false},{"tableIndex":0,"isLast":false,"percentComplete":0,"tableDone":false,"currentRowIndex":0,"count":760},{"percentComplete":0,"tableDone":false,"tableIndex":0,"count":765,"currentRowIndex":0,"isLast":false},{"isLast":false,"tableIndex":0,"currentRowIndex":0,"count":770,"percentComplete":0,"tableDone":false},{"count":775,"tableIndex":0,"tableDone":false,"currentRowIndex":0,"isLast":false,"percentComplete":0},{"isLast":false,"currentRowIndex":0,"tableIndex":0,"tableDone":false,"percentComplete":0,"count":780},{"tableIndex":0,"isLast":false,"percentComplete":0,"currentRowIndex":0,"count":785,"tableDone":false},{"currentRowIndex":0,"tableIndex":0,"tableDone":false,"isLast":false,"percentComplete":0,"count":790},{"tableIndex":0,"tableDone":false,"currentRowIndex":0,"isLast":false,"count":795,"percentComplete":0},{"tableIndex":0,"currentRowIndex":0,"percentComplete":0,"isLast":false,"count":800,"tableDone":false},{"isLast":false,"count":805,"tableIndex":0,"percentComplete":0,"currentRowIndex":0,"tableDone":false},{"tableIndex":0,"count":810,"currentRowIndex":0,"percentComplete":0,"tableDone":false,"isLast":false},{"percentComplete":0,"tableIndex":0,"currentRowIndex":0,"tableDone":false,"isLast":false,"count":815},{"count":820,"percentComplete":0,"tableDone":false,"tableIndex":0,"currentRowIndex":0,"isLast":false},{"currentRowIndex":0,"tableIndex":0,"isLast":false,"count":825,"percentComplete":0,"tableDone":false},{"count":830,"currentRowIndex":0,"percentComplete":0,"tableIndex":0,"tableDone":false,"isLast":false},{"isLast":false,"count":835,"percentComplete":0,"tableIndex":0,"tableDone":false,"currentRowIndex":0},{"percentComplete":0,"isLast":false,"count":840,"tableIndex":0,"currentRowIndex":0,"tableDone":false},{"count":845,"currentRowIndex":0,"tableIndex":0,"isLast":false,"percentComplete":0,"tableDone":false},{"tableDone":false,"currentRowIndex":0,"isLast":false,"percentComplete":0,"count":850,"tableIndex":0},{"tableIndex":0,"currentRowIndex":0,"count":855,"percentComplete":0,"isLast":false,"tableDone":false},{"currentRowIndex":0,"tableIndex":0,"percentComplete":0,"tableDone":false,"isLast":false,"count":860},{"isLast":false,"count":865,"currentRowIndex":0,"tableIndex":0,"percentComplete":0,"tableDone":false},{"tableIndex":0,"percentComplete":0,"tableDone":false,"currentRowIndex":0,"isLast":false,"count":870},{"currentRowIndex":0,"isLast":false,"count":875,"tableDone":false,"percentComplete":0,"tableIndex":0},{"tableIndex":0,"currentRowIndex":0,"percentComplete":0,"count":880,"tableDone":false,"isLast":false},{"tableDone":false,"percentComplete":0,"isLast":false,"tableIndex":0,"count":885,"currentRowIndex":0},{"tableIndex":0,"tableDone":false,"currentRowIndex":0,"isLast":false,"count":890,"percentComplete":0},{"isLast":false,"count":895,"tableDone":false,"percentComplete":0,"tableIndex":0,"currentRowIndex":0},{"isLast":false,"percentComplete":0,"count":900,"tableIndex":0,"tableDone":false,"currentRowIndex":0},{"currentRowIndex":0,"isLast":false,"count":905,"tableIndex":0,"tableDone":false,"percentComplete":0},{"tableIndex":0,"tableDone":false,"isLast":false,"percentComplete":0,"count":910,"currentRowIndex":0},{"tableDone":false,"isLast":false,"percentComplete":0,"tableIndex":0,"currentRowIndex":0,"count":915},{"percentComplete":0,"tableDone":false,"currentRowIndex":0,"isLast":false,"count":920,"tableIndex":0},{"tableIndex":0,"percentComplete":0,"currentRowIndex":0,"isLast":false,"count":925,"tableDone":false},{"tableDone":false,"currentRowIndex":0,"count":930,"tableIndex":0,"isLast":false,"percentComplete":0},{"percentComplete":0,"tableDone":false,"currentRowIndex":0,"isLast":false,"tableIndex":0,"count":935},{"percentComplete":0,"isLast":false,"currentRowIndex":0,"tableIndex":0,"tableDone":false,"count":940},{"isLast":false,"currentRowIndex":0,"tableDone":false,"tableIndex":0,"count":945,"percentComplete":0},{"currentRowIndex":0,"isLast":false,"count":950,"percentComplete":0,"tableIndex":0,"tableDone":true}],"analysedDataType":"datasource","resumableCheckpoint":{"createdDate":"2024-02-12T16:51:33Z","iteration":150,"checkpointURL":"file:\/\/\/Users\/till\/Library\/Caches\/com.apple.dt.createml\/projects\/F276DDE1-0E60-4A85-8EFF-25164205EC6Dc907f12849e2fd37dc5cd5091b8d9a23f12e7e82\/sessions\/checkpoint.sessions\/C2B66F90-7375-40D6-BBAB-CF220D20B269\/training-000000150.checkpoint"},"snapshottableCheckpoints":{"150":{"iteration":150,"createdDate":"2024-02-12T16:51:33Z","modelURL":"file:\/\/\/Users\/till\/Library\/Caches\/com.apple.dt.createml\/projects\/F276DDE1-0E60-4A85-8EFF-25164205EC6Dc907f12849e2fd37dc5cd5091b8d9a23f12e7e82\/sessions\/checkpoint.sessions\/C2B66F90-7375-40D6-BBAB-CF220D20B269\/training-000000150.checkpoint.model\/checkpointModel.mlmodel"}},"validationAccuracy":0.8421052631578947,"snapshottableCheckpointModelURL":"Checkpoints\/C2B66F90-7375-40D6-BBAB-CF220D20B269.ImageClassification10.checkpoint\/training-000000150.checkpoint.model\/checkpointModel.mlmodel","validationResults":{"imageClassifier":{"confusionMatrix":[{"actual":"applegreen","expected":"applegreen","count":6},{"actual":"applegreen","expected":"pear","count":1},{"expected":"peppergreen","count":1,"actual":"applegreen"},{"count":7,"actual":"applered","expected":"applered"},{"actual":"applered","count":1,"expected":"pear"},{"expected":"avocado","actual":"avocado","count":7},{"expected":"cucumber","count":1,"actual":"avocado"},{"count":8,"expected":"banana","actual":"banana"},{"count":1,"expected":"applered","actual":"carrot"},{"actual":"carrot","expected":"carrot","count":7},{"count":6,"actual":"cucumber","expected":"cucumber"},{"expected":"kiwi","count":1,"actual":"cucumber"},{"expected":"pear","count":1,"actual":"cucumber"},{"expected":"kiwi","count":8,"actual":"kiwi"},{"count":1,"actual":"mango","expected":"banana"},{"expected":"kiwi","count":1,"actual":"mango"},{"expected":"mango","count":4,"actual":"mango"},{"actual":"mango","expected":"pepperred","count":1},{"actual":"mango","expected":"tangerine","count":1},{"count":1,"actual":"pear","expected":"carrot"},{"actual":"pear","expected":"pear","count":6},{"expected":"peppergreen","count":7,"actual":"peppergreen"},{"expected":"pepperred","actual":"peppergreen","count":1},{"expected":"peppergreen","count":1,"actual":"pepperred"},{"count":7,"expected":"pepperred","actual":"pepperred"},{"actual":"tangerine","expected":"carrot","count":1},{"actual":"tangerine","expected":"tangerine","count":7}],"accuracy":0.8421052631578947,"statsByLabel":{"applered":{"precisionRecall":{"success":{"precision":0.875,"recall":0.875}},"count":8},"tangerine":{"precisionRecall":{"success":{"precision":0.875,"recall":0.875}},"count":8},"peppergreen":{"precisionRecall":{"success":{"recall":0.875,"precision":0.7777777777777778}},"count":8},"carrot":{"count":8,"precisionRecall":{"success":{"precision":0.7777777777777778,"recall":0.875}}},"mango":{"count":8,"precisionRecall":{"success":{"precision":1,"recall":0.5}}},"pear":{"precisionRecall":{"success":{"recall":0.8571428571428571,"precision":0.6666666666666666}},"count":7},"cucumber":{"count":8,"precisionRecall":{"success":{"precision":0.8571428571428571,"recall":0.75}}},"avocado":{"count":8,"precisionRecall":{"success":{"precision":1,"recall":0.875}}},"kiwi":{"count":8,"precisionRecall":{"success":{"precision":0.8,"recall":1}}},"pepperred":{"count":8,"precisionRecall":{"success":{"recall":0.875,"precision":0.7777777777777778}}},"banana":{"count":8,"precisionRecall":{"success":{"precision":0.8888888888888888,"recall":1}}},"applegreen":{"precisionRecall":{"success":{"recall":0.75,"precision":1}},"count":8}}}},"featureExtractionCheckpointMayBeAvailable":false,"dataResult":{"classesCount":12,"dataURL":"file:\/\/\/Users\/till\/Documents\/Swift%20Student%20Challenge\/01%20datasets%20basic\/","dataSourceID":"6A8516B6-CB84-4F90-B064-E335BF7C3621","createdDate":"2024-02-12T16:49:15Z","itemsCount":950,"dataAnalysis":{"classifierAnalysis":{"labelStats":{"avocado":80,"pear":70,"peppergreen":80,"pepperred":80,"applered":80,"banana":80,"kiwi":80,"applegreen":80,"tangerine":80,"mango":80,"cucumber":80,"carrot":80}},"summary":{"sampleCount":950,"classCount":12,"canUseValidation":1},"issues":[{"severity":"debug","description":"12 classes found, including tangerine, banana, mango"},{"description":"950 images found, automatically creating validation set","severity":"good"},{"severity":"debug","description":"Smallest class is \"pear\" with 70 images"},{"severity":"debug","description":"Largest class is \"tangerine\" with 80 images"}]}},"trainingAccuracy":0.9673130193905817,"trainingResults":{"imageClassifier":{"confusionMatrix":[{"expected":"applegreen","count":138,"actual":"applegreen"},{"actual":"applegreen","expected":"applered","count":1},{"count":2,"actual":"applegreen","expected":"banana"},{"expected":"kiwi","actual":"applegreen","count":3},{"count":1,"actual":"applegreen","expected":"mango"},{"count":4,"expected":"pear","actual":"applegreen"},{"count":2,"actual":"applegreen","expected":"peppergreen"},{"actual":"applegreen","count":1,"expected":"pepperred"},{"expected":"applered","count":148,"actual":"applered"},{"actual":"applered","count":1,"expected":"carrot"},{"count":1,"expected":"kiwi","actual":"applered"},{"expected":"peppergreen","count":1,"actual":"applered"},{"actual":"applered","count":1,"expected":"pepperred"},{"actual":"avocado","count":152,"expected":"avocado"},{"count":1,"actual":"banana","expected":"applegreen"},{"count":145,"actual":"banana","expected":"banana"},{"expected":"cucumber","actual":"banana","count":2},{"actual":"banana","count":3,"expected":"kiwi"},{"expected":"pear","count":1,"actual":"banana"},{"count":1,"actual":"carrot","expected":"banana"},{"actual":"carrot","expected":"carrot","count":149},{"count":1,"actual":"carrot","expected":"mango"},{"count":1,"expected":"tangerine","actual":"carrot"},{"expected":"applegreen","count":1,"actual":"cucumber"},{"expected":"applered","count":1,"actual":"cucumber"},{"count":1,"actual":"cucumber","expected":"banana"},{"actual":"cucumber","expected":"carrot","count":1},{"expected":"cucumber","count":147,"actual":"cucumber"},{"actual":"cucumber","expected":"peppergreen","count":1},{"count":5,"expected":"applegreen","actual":"kiwi"},{"actual":"kiwi","count":1,"expected":"avocado"},{"actual":"kiwi","expected":"banana","count":2},{"count":3,"actual":"kiwi","expected":"cucumber"},{"actual":"kiwi","expected":"kiwi","count":141},{"count":1,"expected":"applered","actual":"mango"},{"count":150,"actual":"mango","expected":"mango"},{"expected":"pepperred","actual":"mango","count":1},{"actual":"pear","count":2,"expected":"mango"},{"actual":"pear","count":131,"expected":"pear"},{"actual":"peppergreen","expected":"applegreen","count":3},{"expected":"avocado","count":1,"actual":"peppergreen"},{"expected":"banana","count":1,"actual":"peppergreen"},{"count":1,"expected":"cucumber","actual":"peppergreen"},{"count":144,"actual":"peppergreen","expected":"peppergreen"},{"count":2,"actual":"peppergreen","expected":"pepperred"},{"count":1,"actual":"pepperred","expected":"applered"},{"expected":"mango","actual":"pepperred","count":1},{"expected":"peppergreen","count":1,"actual":"pepperred"},{"expected":"pepperred","count":149,"actual":"pepperred"},{"actual":"tangerine","expected":"tangerine","count":152}],"accuracy":0.9673130193905817,"statsByLabel":{"avocado":{"count":152,"precisionRecall":{"success":{"recall":1,"precision":0.987012987012987}}},"tangerine":{"precisionRecall":{"success":{"precision":0.9934640522875817,"recall":1}},"count":152},"applegreen":{"count":152,"precisionRecall":{"success":{"recall":0.9078947368421053,"precision":0.9324324324324325}}},"kiwi":{"count":152,"precisionRecall":{"success":{"precision":0.9527027027027027,"recall":0.9276315789473685}}},"mango":{"precisionRecall":{"success":{"precision":0.967741935483871,"recall":0.9868421052631579}},"count":152},"cucumber":{"count":152,"precisionRecall":{"success":{"precision":0.9607843137254902,"recall":0.9671052631578947}}},"banana":{"precisionRecall":{"success":{"recall":0.9539473684210527,"precision":0.9539473684210527}},"count":152},"pepperred":{"precisionRecall":{"success":{"precision":0.9675324675324676,"recall":0.9802631578947368}},"count":152},"peppergreen":{"precisionRecall":{"success":{"recall":0.9473684210526315,"precision":0.9664429530201343}},"count":152},"pear":{"count":133,"precisionRecall":{"success":{"precision":0.9632352941176471,"recall":0.9849624060150376}}},"applered":{"count":152,"precisionRecall":{"success":{"precision":0.9736842105263158,"recall":0.9736842105263158}}},"carrot":{"count":152,"precisionRecall":{"success":{"recall":0.9802631578947368,"precision":0.9867549668874173}}}}}},"finishTime":"2024-02-12T16:51:33Z"},"evaluationState":"uninitialized","title":"Image Classification  10","evaluationContainerEntity":{"id":"150a2353-f9e0-435a-9896-335c8dbeaf4d","modifiedDate":"2024-02-12T17:17:08Z","createdDate":"2024-02-12T17:17:08Z","trainingEvaluationEntity":{"evaluationResult":{"imageClassifier":{"statsByLabel":{"kiwi":{"precisionRecall":{"success":{"precision":0.9527027027027027,"recall":0.9276315789473685}},"count":152},"carrot":{"precisionRecall":{"success":{"precision":0.9867549668874173,"recall":0.9802631578947368}},"count":152},"banana":{"count":152,"precisionRecall":{"success":{"precision":0.9539473684210527,"recall":0.9539473684210527}}},"mango":{"count":152,"precisionRecall":{"success":{"precision":0.967741935483871,"recall":0.9868421052631579}}},"avocado":{"count":152,"precisionRecall":{"success":{"recall":1,"precision":0.987012987012987}}},"peppergreen":{"precisionRecall":{"success":{"precision":0.9664429530201343,"recall":0.9473684210526315}},"count":152},"cucumber":{"count":152,"precisionRecall":{"success":{"precision":0.9607843137254902,"recall":0.9671052631578947}}},"pear":{"count":133,"precisionRecall":{"success":{"recall":0.9849624060150376,"precision":0.9632352941176471}}},"tangerine":{"precisionRecall":{"success":{"precision":0.9934640522875817,"recall":1}},"count":152},"applegreen":{"count":152,"precisionRecall":{"success":{"recall":0.9078947368421053,"precision":0.9324324324324325}}},"applered":{"precisionRecall":{"success":{"precision":0.9736842105263158,"recall":0.9736842105263158}},"count":152},"pepperred":{"count":152,"precisionRecall":{"success":{"precision":0.9675324675324676,"recall":0.9802631578947368}}}},"confusionMatrix":[{"actual":"applegreen","expected":"applegreen","count":138},{"expected":"applered","actual":"applegreen","count":1},{"actual":"applegreen","count":2,"expected":"banana"},{"actual":"applegreen","count":3,"expected":"kiwi"},{"actual":"applegreen","expected":"mango","count":1},{"count":4,"expected":"pear","actual":"applegreen"},{"count":2,"actual":"applegreen","expected":"peppergreen"},{"actual":"applegreen","count":1,"expected":"pepperred"},{"expected":"applered","count":148,"actual":"applered"},{"actual":"applered","count":1,"expected":"carrot"},{"count":1,"actual":"applered","expected":"kiwi"},{"expected":"peppergreen","count":1,"actual":"applered"},{"actual":"applered","count":1,"expected":"pepperred"},{"expected":"avocado","count":152,"actual":"avocado"},{"actual":"banana","expected":"applegreen","count":1},{"actual":"banana","expected":"banana","count":145},{"expected":"cucumber","count":2,"actual":"banana"},{"expected":"kiwi","count":3,"actual":"banana"},{"expected":"pear","count":1,"actual":"banana"},{"actual":"carrot","count":1,"expected":"banana"},{"expected":"carrot","count":149,"actual":"carrot"},{"count":1,"actual":"carrot","expected":"mango"},{"count":1,"expected":"tangerine","actual":"carrot"},{"count":1,"actual":"cucumber","expected":"applegreen"},{"actual":"cucumber","count":1,"expected":"applered"},{"actual":"cucumber","expected":"banana","count":1},{"count":1,"actual":"cucumber","expected":"carrot"},{"expected":"cucumber","count":147,"actual":"cucumber"},{"count":1,"expected":"peppergreen","actual":"cucumber"},{"count":5,"expected":"applegreen","actual":"kiwi"},{"count":1,"expected":"avocado","actual":"kiwi"},{"actual":"kiwi","expected":"banana","count":2},{"actual":"kiwi","count":3,"expected":"cucumber"},{"actual":"kiwi","expected":"kiwi","count":141},{"expected":"applered","count":1,"actual":"mango"},{"count":150,"actual":"mango","expected":"mango"},{"count":1,"actual":"mango","expected":"pepperred"},{"actual":"pear","expected":"mango","count":2},{"expected":"pear","count":131,"actual":"pear"},{"expected":"applegreen","actual":"peppergreen","count":3},{"count":1,"actual":"peppergreen","expected":"avocado"},{"actual":"peppergreen","expected":"banana","count":1},{"count":1,"expected":"cucumber","actual":"peppergreen"},{"count":144,"actual":"peppergreen","expected":"peppergreen"},{"actual":"peppergreen","count":2,"expected":"pepperred"},{"actual":"pepperred","expected":"applered","count":1},{"count":1,"actual":"pepperred","expected":"mango"},{"expected":"peppergreen","count":1,"actual":"pepperred"},{"expected":"pepperred","actual":"pepperred","count":149},{"count":152,"actual":"tangerine","expected":"tangerine"}],"accuracy":0.9673130193905817}},"analysedDataType":"none","id":"b57c6ab1-7bc3-42a2-8e50-c5aa6906d172","dataSourceID":"6A8516B6-CB84-4F90-B064-E335BF7C3621","dataResult":{"dataAnalysis":{"classifierAnalysis":{"labelStats":{"cucumber":80,"applered":80,"applegreen":80,"avocado":80,"banana":80,"pear":70,"peppergreen":80,"kiwi":80,"carrot":80,"pepperred":80,"tangerine":80,"mango":80}},"summary":{"classCount":12,"sampleCount":950,"canUseValidation":1},"issues":[{"severity":"debug","description":"12 classes found, including tangerine, banana, mango"},{"description":"950 images found, automatically creating validation set","severity":"good"},{"description":"Smallest class is \"pear\" with 70 images","severity":"debug"},{"severity":"debug","description":"Largest class is \"tangerine\" with 80 images"}]},"dataURL":"file:\/\/\/Users\/till\/Documents\/Swift%20Student%20Challenge\/01%20datasets%20basic\/","dataSourceID":"6A8516B6-CB84-4F90-B064-E335BF7C3621","itemsCount":950,"classesCount":12,"createdDate":"2024-02-12T16:49:15Z"},"createdDate":"2024-02-12T16:49:15Z"},"evaluationEntities":[{"createdDate":"2024-02-12T16:51:38Z","analysedDataType":"none","id":"0e036e90-4a96-404b-bd47-45b3c66240c2","dataResult":{"createdDate":"2024-02-12T17:01:37Z"}}],"previewType":"imageClassifier","validationEvaluationEntity":{"evaluationResult":{"imageClassifier":{"accuracy":0.8421052631578947,"statsByLabel":{"mango":{"precisionRecall":{"success":{"recall":0.5,"precision":1}},"count":8},"tangerine":{"precisionRecall":{"success":{"recall":0.875,"precision":0.875}},"count":8},"avocado":{"precisionRecall":{"success":{"precision":1,"recall":0.875}},"count":8},"applegreen":{"precisionRecall":{"success":{"recall":0.75,"precision":1}},"count":8},"banana":{"count":8,"precisionRecall":{"success":{"recall":1,"precision":0.8888888888888888}}},"pepperred":{"count":8,"precisionRecall":{"success":{"recall":0.875,"precision":0.7777777777777778}}},"carrot":{"precisionRecall":{"success":{"recall":0.875,"precision":0.7777777777777778}},"count":8},"applered":{"count":8,"precisionRecall":{"success":{"precision":0.875,"recall":0.875}}},"peppergreen":{"precisionRecall":{"success":{"precision":0.7777777777777778,"recall":0.875}},"count":8},"kiwi":{"count":8,"precisionRecall":{"success":{"precision":0.8,"recall":1}}},"pear":{"count":7,"precisionRecall":{"success":{"precision":0.6666666666666666,"recall":0.8571428571428571}}},"cucumber":{"precisionRecall":{"success":{"precision":0.8571428571428571,"recall":0.75}},"count":8}},"confusionMatrix":[{"count":6,"expected":"applegreen","actual":"applegreen"},{"actual":"applegreen","expected":"pear","count":1},{"actual":"applegreen","expected":"peppergreen","count":1},{"count":7,"actual":"applered","expected":"applered"},{"actual":"applered","count":1,"expected":"pear"},{"actual":"avocado","count":7,"expected":"avocado"},{"actual":"avocado","count":1,"expected":"cucumber"},{"expected":"banana","count":8,"actual":"banana"},{"actual":"carrot","expected":"applered","count":1},{"actual":"carrot","expected":"carrot","count":7},{"count":6,"actual":"cucumber","expected":"cucumber"},{"count":1,"actual":"cucumber","expected":"kiwi"},{"actual":"cucumber","expected":"pear","count":1},{"count":8,"expected":"kiwi","actual":"kiwi"},{"expected":"banana","count":1,"actual":"mango"},{"count":1,"actual":"mango","expected":"kiwi"},{"expected":"mango","count":4,"actual":"mango"},{"actual":"mango","expected":"pepperred","count":1},{"expected":"tangerine","actual":"mango","count":1},{"actual":"pear","count":1,"expected":"carrot"},{"count":6,"actual":"pear","expected":"pear"},{"count":7,"actual":"peppergreen","expected":"peppergreen"},{"expected":"pepperred","actual":"peppergreen","count":1},{"actual":"pepperred","count":1,"expected":"peppergreen"},{"expected":"pepperred","actual":"pepperred","count":7},{"count":1,"actual":"tangerine","expected":"carrot"},{"count":7,"actual":"tangerine","expected":"tangerine"}]}},"createdDate":"2024-02-12T16:49:15Z","id":"c7e2e814-3ea0-47e5-85d2-30ce99e0588e","analysedDataType":"auto","dataResult":{"createdDate":"2024-02-12T16:49:15Z"}},"testingEvaluationEntity":{"dataResult":{"createdDate":"2024-02-12T16:49:15Z"},"createdDate":"2024-02-12T16:49:15Z","id":"f479b589-d904-4d2a-907e-9568ae3a7787","analysedDataType":"none"}},"settingEntity":{"handPoseClassifierAugmentations":[],"seedType":"default","transferLearningEmbeddingType":"dynamic","handActionClassifierAugmentations":[],"styleTransferAlgorithmType":"image","algorithmType":"maxEnt","augmentations":["flip","addNoise","blur","expose","rotate"],"iterationCount":125,"harVideoAugmentations":0,"taskType":"imageClassifier","featureExtractorType":"scenePrintV2","featureNames":[]}}