{"title":"Iteration 150","contentDataResult":{"createdDate":"2024-02-12T16:49:15Z"},"evaluationEntity":{"dataResult":{},"analysedDataType":"none","id":"42cc8f12-ded2-4e15-b538-e7450c13cc6e"},"modifiedDate":"2024-02-13T10:49:30Z","version":"1.0","modelEntity":{"modifiedDate":"2024-02-13T10:49:30Z","preferredFilename":"","experimentID":"D461835D-E3E6-4D61-B0FC-9BF740863B92","createdDate":"2024-02-13T10:49:30Z","title":"","modelURL":"Snapshots\/Image%20Classification%20%2011%20Iteration%20150.mlmodel","id":"982C41AA-84E4-4B3E-AD8D-4607D11C9684","version":"1.0"},"activityEntities":["trainingFinished",[{"title":"Training Completed","id":"89FF2532-A35D-4610-B2E3-597D175BEB6A","createdDate":"2024-02-13T10:49:27Z","subtitle":"Model converged at 25 iterations","event":"trainingFinished"}],"experimentCreated",[{"subtitle":"Image Classification  11","event":"experimentCreated","id":"D55E751B-A1CB-464D-A696-401467F6CF31","title":"Model Source Created","createdDate":"2024-02-12T17:17:08Z"}],"trainingDataAdded",[{"id":"4D1C2525-E4E6-40D3-81E9-3DCC9916AA71","event":"trainingDataAdded","subtitle":"01 datasets basic","createdDate":"2024-02-12T18:13:22Z","title":"Training Data Added"}],"trainingExtended",[{"event":"trainingExtended","id":"8F91E332-2177-48DA-87FC-06FD9F013FF9","createdDate":"2024-02-12T18:14:01Z","subtitle":"20 more iterations","title":"Training Extended"},{"id":"37D0066E-5576-445C-AA50-D4005030E594","createdDate":"2024-02-12T18:14:06Z","title":"Training Extended","subtitle":"20 more iterations","event":"trainingExtended"},{"createdDate":"2024-02-13T10:49:20Z","event":"trainingExtended","id":"254D9FE3-8856-459E-A2AD-FDE03C5BE479","subtitle":"20 more iterations","title":"Training Extended"},{"title":"Training Extended","id":"3D98B34D-D42E-46ED-884F-74C0BC35B5B3","subtitle":"20 more iterations","event":"trainingExtended","createdDate":"2024-02-13T10:49:23Z"},{"id":"F5CD8217-8B5A-4ABF-A3F9-93E77BF8DE16","createdDate":"2024-02-13T10:49:26Z","title":"Training Extended","event":"trainingExtended","subtitle":"20 more iterations"}],"trainingStarted",[{"title":"Training Started","id":"D7E7FFB0-F41A-4922-A5C1-65308AF2DD26","event":"trainingStarted","subtitle":"25 iterations","createdDate":"2024-02-12T18:13:36Z"}],"snapshotCreated",[{"id":"2DC0D3D4-6F5C-4F63-8EF0-8449BA1D90CB","subtitle":"Snapshot created at iteration 25","event":"snapshotCreated","createdDate":"2024-02-12T18:14:01Z","title":"Snapshot Saved"},{"id":"4558DA47-28B4-488C-B8F9-97007A2B7246","event":"snapshotCreated","subtitle":"Snapshot created at iteration 50","createdDate":"2024-02-12T18:14:06Z","title":"Snapshot Saved"},{"event":"snapshotCreated","title":"Snapshot Saved","id":"57A43865-54ED-4A54-9B0C-B7FFC0CD0CAD","subtitle":"Snapshot created at iteration 75","createdDate":"2024-02-13T10:49:20Z"},{"createdDate":"2024-02-13T10:49:23Z","event":"snapshotCreated","title":"Snapshot Saved","id":"4A5A8FBC-7AB9-4A5F-B05A-E019088157DB","subtitle":"Snapshot created at iteration 100"},{"createdDate":"2024-02-13T10:49:26Z","id":"C171B0BA-EFCC-4AC4-9851-B749D8C73F8C","subtitle":"Snapshot created at iteration 125","title":"Snapshot Saved","event":"snapshotCreated"}]],"evaluationState":"uninitialized","validationEntity":{"analysedDataType":"auto","dataResult":{"createdDate":"2024-02-13T10:49:30Z"}},"evaluationContainerEntity":{"createdDate":"2024-02-13T10:49:30Z","id":"7b03fb89-4179-4414-8c19-55e2d32581df","testingEvaluationEntity":{"dataResult":{"createdDate":"2024-02-13T10:49:30Z"},"analysedDataType":"none","id":"5665412c-1b5e-46cb-898a-34587ca59163","createdDate":"2024-02-13T10:49:30Z"},"modifiedDate":"2024-02-13T10:49:30Z","previewType":"imageClassifier","evaluationEntities":[],"trainingEvaluationEntity":{"analysedDataType":"none","createdDate":"2024-02-13T10:49:30Z","dataResult":{"dataURL":"file:\/\/\/Users\/till\/Documents\/Swift%20Student%20Challenge\/01%20datasets%20basic\/","createdDate":"2024-02-13T10:49:30Z","dataSourceID":"6A8516B6-CB84-4F90-B064-E335BF7C3621"},"id":"865a8604-cc9c-4d43-bf4f-5528abdfe50a","dataSourceID":"6A8516B6-CB84-4F90-B064-E335BF7C3621"},"validationEvaluationEntity":{"analysedDataType":"auto","id":"7526b014-237f-4d87-a694-bbbbfec578d4","createdDate":"2024-02-13T10:49:30Z","dataResult":{"createdDate":"2024-02-13T10:49:30Z"}}},"createdDate":"2024-02-13T10:49:30Z","trainingEntity":{"startTime":"2024-02-13T10:49:26Z","checkpointMetrics":{"150":{"iteration":150,"metrics":{},"createdDate":"2024-02-13T10:49:27Z"},"25":{"iteration":25,"createdDate":"2024-02-12T18:13:57Z","metrics":{}},"50":{"metrics":{},"createdDate":"2024-02-12T18:14:03Z","iteration":50},"100":{"metrics":{},"createdDate":"2024-02-13T10:49:21Z","iteration":100},"75":{"metrics":{},"iteration":75,"createdDate":"2024-02-12T18:14:07Z"},"125":{"createdDate":"2024-02-13T10:49:24Z","iteration":125,"metrics":{}}},"progress":[{"icTrainingColumnHeader":{"iterationCount":2,"hasValidation":true,"elapsedTime":0.08169102668762207,"trainingAccuracy":0.5912110373019929,"validationAccuracy":0.5436893203883495},"count":2,"percentComplete":0,"tableIndex":1,"currentRowIndex":0,"isLast":false,"tableDone":false},{"percentComplete":0,"currentRowIndex":0,"count":3,"tableDone":false,"tableIndex":1,"icTrainingColumnHeader":{"iterationCount":3,"validationAccuracy":0.6116504854368932,"elapsedTime":0.11255502700805664,"trainingAccuracy":0.660705160960654,"hasValidation":true},"isLast":false},{"icTrainingColumnHeader":{"iterationCount":4,"elapsedTime":0.13255798816680908,"hasValidation":true,"trainingAccuracy":0.6990291262135923,"validationAccuracy":0.6601941747572816},"count":4,"isLast":false,"tableIndex":0,"currentRowIndex":0,"tableDone":false,"percentComplete":0},{"count":5,"percentComplete":0,"tableIndex":1,"currentRowIndex":0,"icTrainingColumnHeader":{"elapsedTime":0.15191400051116943,"hasValidation":true,"iterationCount":5,"trainingAccuracy":0.715891670924885,"validationAccuracy":0.6504854368932039},"tableDone":false,"isLast":false},{"isLast":false,"count":10,"percentComplete":0,"tableIndex":0,"tableDone":false,"currentRowIndex":0},{"percentComplete":0,"icTrainingColumnHeader":{"elapsedTime":0.285910964012146,"validationAccuracy":0.7669902912621359,"hasValidation":true,"trainingAccuracy":0.8487480838017374,"iterationCount":11},"tableDone":false,"tableIndex":0,"count":11,"currentRowIndex":0,"isLast":false},{"count":15,"percentComplete":0,"isLast":false,"tableDone":true,"currentRowIndex":0,"tableIndex":0,"icTrainingColumnHeader":{"elapsedTime":0.574070930480957,"validationAccuracy":0.7961165048543689,"hasValidation":true,"trainingAccuracy":0.8840061318344404,"iterationCount":15}},{"currentRowIndex":0,"tableIndex":0,"isLast":false,"percentComplete":0,"count":16,"tableDone":true,"icTrainingColumnHeader":{"elapsedTime":0.4105980396270752,"iterationCount":16,"validationAccuracy":0.7961165048543689,"hasValidation":true,"trainingAccuracy":0.8911599386816556}},{"currentRowIndex":0,"icTrainingColumnHeader":{"hasValidation":true,"iterationCount":18,"elapsedTime":0.43967700004577637,"trainingAccuracy":0.9177312212570261,"validationAccuracy":0.7378640776699029},"percentComplete":0,"tableDone":true,"tableIndex":0,"count":18,"isLast":false},{"currentRowIndex":0,"count":20,"percentComplete":0,"tableIndex":0,"isLast":false,"tableDone":false},{"isLast":false,"tableIndex":1,"icTrainingColumnHeader":{"elapsedTime":0.5866389274597168,"validationAccuracy":0.7961165048543689,"iterationCount":21,"hasValidation":true,"trainingAccuracy":0.9253960143076136},"count":21,"percentComplete":0,"tableDone":false,"currentRowIndex":0},{"percentComplete":0,"isLast":false,"count":25,"icTrainingColumnHeader":{"hasValidation":true,"trainingAccuracy":0.9555442003065917,"validationAccuracy":0.7864077669902912,"iterationCount":25,"elapsedTime":0.6753389835357666},"tableDone":true,"currentRowIndex":0,"tableIndex":0},{"tableIndex":0,"isLast":false,"count":30,"currentRowIndex":0,"tableDone":false,"percentComplete":0},{"tableIndex":0,"currentRowIndex":0,"isLast":false,"count":35,"percentComplete":0,"tableDone":false},{"currentRowIndex":0,"tableIndex":0,"isLast":false,"percentComplete":0,"count":40,"tableDone":false},{"count":45,"percentComplete":0,"isLast":false,"tableIndex":0,"tableDone":false,"currentRowIndex":0},{"tableDone":false,"isLast":false,"count":50,"currentRowIndex":0,"percentComplete":0,"tableIndex":0},{"currentRowIndex":0,"tableDone":false,"count":55,"tableIndex":0,"percentComplete":0,"isLast":false},{"percentComplete":0,"tableDone":false,"currentRowIndex":0,"isLast":false,"tableIndex":0,"count":60},{"tableIndex":0,"percentComplete":0,"currentRowIndex":0,"tableDone":false,"isLast":false,"count":65},{"tableDone":false,"count":70,"tableIndex":0,"percentComplete":0,"isLast":false,"currentRowIndex":0},{"tableDone":false,"tableIndex":0,"percentComplete":0,"currentRowIndex":0,"isLast":false,"count":75},{"percentComplete":0,"tableDone":false,"currentRowIndex":0,"tableIndex":0,"isLast":false,"count":80},{"count":85,"tableIndex":0,"isLast":false,"currentRowIndex":0,"tableDone":false,"percentComplete":0},{"isLast":false,"count":90,"tableDone":false,"tableIndex":0,"percentComplete":0,"currentRowIndex":0},{"count":95,"percentComplete":0,"tableDone":false,"currentRowIndex":0,"tableIndex":0,"isLast":false},{"count":100,"tableIndex":0,"percentComplete":0,"isLast":false,"currentRowIndex":0,"tableDone":false},{"tableDone":false,"isLast":false,"currentRowIndex":0,"tableIndex":0,"count":105,"percentComplete":0},{"tableDone":false,"percentComplete":0,"tableIndex":0,"isLast":false,"count":110,"currentRowIndex":0},{"tableDone":false,"currentRowIndex":0,"tableIndex":0,"isLast":false,"count":115,"percentComplete":0},{"percentComplete":0,"tableDone":false,"isLast":false,"currentRowIndex":0,"tableIndex":0,"count":120},{"count":125,"percentComplete":0,"currentRowIndex":0,"isLast":false,"tableIndex":0,"tableDone":false},{"isLast":false,"count":130,"currentRowIndex":0,"percentComplete":0,"tableIndex":0,"tableDone":false},{"percentComplete":0,"isLast":false,"count":135,"currentRowIndex":0,"tableIndex":0,"tableDone":false},{"currentRowIndex":0,"tableDone":false,"isLast":false,"percentComplete":0,"tableIndex":0,"count":140},{"tableIndex":0,"tableDone":false,"count":145,"currentRowIndex":0,"percentComplete":0,"isLast":false},{"tableIndex":0,"tableDone":false,"currentRowIndex":0,"isLast":false,"count":150,"percentComplete":0}],"featureExtractionCheckpointMayBeAvailable":false,"analysedDataType":"datasource","dataResult":{"classesCount":13,"dataAnalysis":{"classifierAnalysis":{"labelStats":{"kiwi":80,"applegreen":80,"pepperred":80,"applered":80,"pepperyellow":80,"tangerine":80,"banana":80,"pear":70,"mango":80,"peppergreen":80,"cucumber":80,"carrot":80,"avocado":80}},"summary":{"classCount":13,"canUseValidation":1,"sampleCount":1030},"issues":[{"severity":"debug","description":"13 classes found, including pepperred, carrot, kiwi"},{"severity":"good","description":"1030 images found, automatically creating validation set"},{"severity":"debug","description":"Smallest class is \"pear\" with 70 images"},{"description":"Largest class is \"pepperred\" with 80 images","severity":"debug"}]},"itemsCount":1030,"dataSourceID":"6A8516B6-CB84-4F90-B064-E335BF7C3621","createdDate":"2024-02-13T10:49:30Z","dataURL":"file:\/\/\/Users\/till\/Documents\/Swift%20Student%20Challenge\/01%20datasets%20basic\/"},"trainingAccuracy":0.9177312212570261,"snapshottableCheckpoints":{"150":{"createdDate":"2024-02-13T10:49:27Z","modelURL":"file:\/\/\/Users\/till\/Library\/Caches\/com.apple.dt.createml\/projects\/F276DDE1-0E60-4A85-8EFF-25164205EC6Dc907f12849e2fd37dc5cd5091b8d9a23f12e7e82\/sessions\/checkpoint.sessions\/DF871C18-11D5-44B5-8B49-A049684F9661\/training-000000150.checkpoint.model\/checkpointModel.mlmodel","iteration":150}},"resumableCheckpoint":{"createdDate":"2024-02-13T10:49:27Z","checkpointURL":"file:\/\/\/Users\/till\/Library\/Caches\/com.apple.dt.createml\/projects\/F276DDE1-0E60-4A85-8EFF-25164205EC6Dc907f12849e2fd37dc5cd5091b8d9a23f12e7e82\/sessions\/checkpoint.sessions\/DF871C18-11D5-44B5-8B49-A049684F9661\/training-000000150.checkpoint","iteration":150},"finishTime":"2024-02-13T10:49:27Z","trainingResults":{"imageClassifier":{"accuracy":0.9177312212570261,"confusionMatrix":[{"expected":"applegreen","count":127,"actual":"applegreen"},{"actual":"applegreen","expected":"avocado","count":7},{"count":2,"expected":"banana","actual":"applegreen"},{"expected":"carrot","actual":"applegreen","count":3},{"expected":"kiwi","count":1,"actual":"applegreen"},{"count":1,"actual":"applegreen","expected":"mango"},{"actual":"applegreen","count":4,"expected":"pear"},{"actual":"applegreen","expected":"peppergreen","count":6},{"count":1,"actual":"applegreen","expected":"pepperyellow"},{"actual":"applered","count":146,"expected":"applered"},{"count":1,"expected":"avocado","actual":"applered"},{"expected":"carrot","count":2,"actual":"applered"},{"count":2,"expected":"mango","actual":"applered"},{"count":1,"actual":"applered","expected":"tangerine"},{"expected":"applegreen","count":1,"actual":"avocado"},{"count":138,"actual":"avocado","expected":"avocado"},{"expected":"banana","actual":"avocado","count":1},{"actual":"avocado","count":2,"expected":"carrot"},{"expected":"cucumber","actual":"avocado","count":3},{"count":5,"actual":"avocado","expected":"kiwi"},{"count":2,"expected":"peppergreen","actual":"avocado"},{"count":1,"actual":"banana","expected":"applegreen"},{"actual":"banana","expected":"applered","count":1},{"count":136,"expected":"banana","actual":"banana"},{"expected":"carrot","count":3,"actual":"banana"},{"expected":"cucumber","count":1,"actual":"banana"},{"actual":"banana","expected":"kiwi","count":3},{"expected":"mango","actual":"banana","count":1},{"actual":"banana","expected":"pear","count":5},{"actual":"banana","expected":"tangerine","count":1},{"count":1,"expected":"avocado","actual":"carrot"},{"expected":"banana","actual":"carrot","count":2},{"count":143,"actual":"carrot","expected":"carrot"},{"actual":"carrot","expected":"cucumber","count":1},{"count":1,"actual":"carrot","expected":"mango"},{"actual":"carrot","expected":"pear","count":1},{"expected":"peppergreen","count":1,"actual":"carrot"},{"expected":"tangerine","actual":"carrot","count":2},{"expected":"applegreen","actual":"cucumber","count":1},{"count":2,"expected":"carrot","actual":"cucumber"},{"actual":"cucumber","expected":"cucumber","count":146},{"actual":"cucumber","expected":"pepperred","count":1},{"actual":"cucumber","expected":"pepperyellow","count":2},{"actual":"kiwi","expected":"applegreen","count":5},{"expected":"applered","actual":"kiwi","count":1},{"actual":"kiwi","expected":"avocado","count":2},{"expected":"banana","count":1,"actual":"kiwi"},{"expected":"carrot","count":3,"actual":"kiwi"},{"actual":"kiwi","count":1,"expected":"cucumber"},{"expected":"kiwi","count":136,"actual":"kiwi"},{"actual":"kiwi","expected":"pear","count":1},{"actual":"kiwi","expected":"pepperyellow","count":1},{"count":1,"actual":"kiwi","expected":"tangerine"},{"expected":"applegreen","count":1,"actual":"mango"},{"expected":"applered","count":3,"actual":"mango"},{"actual":"mango","expected":"avocado","count":1},{"actual":"mango","expected":"banana","count":2},{"count":2,"expected":"carrot","actual":"mango"},{"expected":"kiwi","actual":"mango","count":2},{"count":135,"expected":"mango","actual":"mango"},{"count":1,"actual":"mango","expected":"peppergreen"},{"count":2,"actual":"mango","expected":"pepperyellow"},{"count":3,"actual":"mango","expected":"tangerine"},{"actual":"pear","expected":"applegreen","count":1},{"expected":"applered","count":1,"actual":"pear"},{"actual":"pear","count":1,"expected":"banana"},{"expected":"carrot","count":1,"actual":"pear"},{"expected":"cucumber","actual":"pear","count":2},{"expected":"kiwi","count":1,"actual":"pear"},{"count":1,"expected":"mango","actual":"pear"},{"count":121,"expected":"pear","actual":"pear"},{"actual":"pear","count":1,"expected":"peppergreen"},{"actual":"pear","expected":"pepperyellow","count":3},{"expected":"avocado","count":4,"actual":"peppergreen"},{"expected":"banana","count":1,"actual":"peppergreen"},{"actual":"peppergreen","count":3,"expected":"cucumber"},{"actual":"peppergreen","expected":"peppergreen","count":138},{"count":2,"actual":"peppergreen","expected":"pepperred"},{"expected":"pepperyellow","actual":"peppergreen","count":2},{"actual":"peppergreen","expected":"tangerine","count":2},{"count":2,"actual":"pepperred","expected":"applered"},{"expected":"banana","actual":"pepperred","count":1},{"actual":"pepperred","expected":"cucumber","count":1},{"actual":"pepperred","count":1,"expected":"mango"},{"expected":"peppergreen","actual":"pepperred","count":1},{"expected":"pepperred","count":145,"actual":"pepperred"},{"actual":"pepperred","count":1,"expected":"pepperyellow"},{"actual":"pepperyellow","expected":"banana","count":1},{"expected":"carrot","count":1,"actual":"pepperyellow"},{"actual":"pepperyellow","expected":"mango","count":2},{"count":1,"actual":"pepperyellow","expected":"pear"},{"count":3,"expected":"peppergreen","actual":"pepperyellow"},{"expected":"pepperred","actual":"pepperyellow","count":2},{"expected":"pepperyellow","count":142,"actual":"pepperyellow"},{"actual":"tangerine","expected":"carrot","count":3},{"expected":"mango","count":2,"actual":"tangerine"},{"count":2,"actual":"tangerine","expected":"pepperred"},{"actual":"tangerine","expected":"pepperyellow","count":2},{"count":143,"expected":"tangerine","actual":"tangerine"}],"statsByLabel":{"avocado":{"count":152,"precisionRecall":{"success":{"precision":0.8961038961038961,"recall":0.9078947368421053}}},"mango":{"precisionRecall":{"success":{"recall":0.8881578947368421,"precision":0.9246575342465754}},"count":152},"kiwi":{"count":152,"precisionRecall":{"success":{"recall":0.8947368421052632,"precision":0.918918918918919}}},"pepperyellow":{"count":152,"precisionRecall":{"success":{"precision":0.9102564102564102,"recall":0.9342105263157895}}},"tangerine":{"precisionRecall":{"success":{"recall":0.9407894736842105,"precision":0.934640522875817}},"count":152},"banana":{"count":152,"precisionRecall":{"success":{"precision":0.918918918918919,"recall":0.8947368421052632}}},"cucumber":{"precisionRecall":{"success":{"recall":0.9605263157894737,"precision":0.9240506329113924}},"count":152},"pepperred":{"count":152,"precisionRecall":{"success":{"precision":0.9539473684210527,"recall":0.9539473684210527}}},"carrot":{"precisionRecall":{"success":{"recall":0.9407894736842105,"precision":0.8666666666666667}},"count":152},"applegreen":{"precisionRecall":{"success":{"recall":0.8355263157894737,"precision":0.927007299270073}},"count":152},"applered":{"count":152,"precisionRecall":{"success":{"precision":0.948051948051948,"recall":0.9605263157894737}}},"pear":{"precisionRecall":{"success":{"precision":0.9097744360902256,"recall":0.9097744360902256}},"count":133},"peppergreen":{"precisionRecall":{"success":{"recall":0.9078947368421053,"precision":0.9019607843137255}},"count":152}}}},"dataSourceID":"6A8516B6-CB84-4F90-B064-E335BF7C3621","validationResults":{"imageClassifier":{"accuracy":0.7378640776699029,"statsByLabel":{"peppergreen":{"precisionRecall":{"success":{"precision":0.625,"recall":0.625}},"count":8},"pepperyellow":{"count":8,"precisionRecall":{"success":{"recall":0.625,"precision":0.7142857142857143}}},"cucumber":{"precisionRecall":{"success":{"precision":0.8333333333333334,"recall":0.625}},"count":8},"banana":{"count":8,"precisionRecall":{"success":{"precision":0.625,"recall":0.625}}},"tangerine":{"count":8,"precisionRecall":{"success":{"recall":0.875,"precision":0.875}}},"carrot":{"count":8,"precisionRecall":{"success":{"precision":0.6363636363636364,"recall":0.875}}},"applegreen":{"count":8,"precisionRecall":{"success":{"recall":0.875,"precision":0.875}}},"pepperred":{"precisionRecall":{"success":{"precision":0.5714285714285714,"recall":0.5}},"count":8},"avocado":{"count":8,"precisionRecall":{"success":{"precision":0.8888888888888888,"recall":1}}},"kiwi":{"count":8,"precisionRecall":{"success":{"precision":0.875,"recall":0.875}}},"mango":{"precisionRecall":{"success":{"recall":0.5,"precision":0.8}},"count":8},"pear":{"count":7,"precisionRecall":{"success":{"recall":1,"precision":0.7777777777777778}}},"applered":{"precisionRecall":{"success":{"recall":0.625,"precision":0.5555555555555556}},"count":8}},"confusionMatrix":[{"expected":"applegreen","count":7,"actual":"applegreen"},{"count":1,"expected":"pear","actual":"applegreen"},{"actual":"applered","count":5,"expected":"applered"},{"actual":"applered","count":1,"expected":"banana"},{"expected":"carrot","actual":"applered","count":1},{"expected":"pepperred","count":1,"actual":"applered"},{"expected":"avocado","actual":"avocado","count":8},{"count":1,"actual":"banana","expected":"avocado"},{"actual":"banana","expected":"banana","count":5},{"actual":"banana","count":1,"expected":"cucumber"},{"actual":"banana","count":1,"expected":"kiwi"},{"expected":"banana","count":1,"actual":"carrot"},{"expected":"carrot","count":7,"actual":"carrot"},{"expected":"applered","actual":"cucumber","count":1},{"actual":"cucumber","expected":"carrot","count":1},{"actual":"cucumber","count":5,"expected":"cucumber"},{"count":1,"actual":"cucumber","expected":"peppergreen"},{"actual":"kiwi","expected":"kiwi","count":7},{"expected":"pear","count":1,"actual":"kiwi"},{"count":1,"actual":"mango","expected":"banana"},{"expected":"carrot","count":1,"actual":"mango"},{"expected":"mango","count":4,"actual":"mango"},{"actual":"mango","count":1,"expected":"pepperyellow"},{"count":1,"actual":"mango","expected":"tangerine"},{"count":7,"actual":"pear","expected":"pear"},{"count":1,"actual":"peppergreen","expected":"applered"},{"actual":"peppergreen","count":5,"expected":"peppergreen"},{"count":1,"expected":"pepperred","actual":"peppergreen"},{"count":1,"actual":"peppergreen","expected":"pepperyellow"},{"expected":"applered","count":2,"actual":"pepperred"},{"actual":"pepperred","expected":"mango","count":1},{"actual":"pepperred","expected":"peppergreen","count":1},{"count":4,"expected":"pepperred","actual":"pepperred"},{"count":1,"expected":"applegreen","actual":"pepperyellow"},{"actual":"pepperyellow","expected":"peppergreen","count":1},{"count":1,"actual":"pepperyellow","expected":"pepperred"},{"actual":"pepperyellow","expected":"pepperyellow","count":5},{"actual":"tangerine","expected":"carrot","count":1},{"actual":"tangerine","expected":"tangerine","count":7}]}},"validationAccuracy":0.7378640776699029},"preferredFilename":"Image Classification  11 Iteration 150","state":"trained","snapshotRole":{"snapshotIteration":150,"snapshotParent":"DF871C18-11D5-44B5-8B49-A049684F9661"},"settingEntity":{"augmentations":["blur","expose","flip","addNoise","rotate"],"harVideoAugmentations":0,"taskType":"imageClassifier","featureNames":[],"seedType":"default","handPoseClassifierAugmentations":[],"algorithmType":"maxEnt","featureExtractorType":"scenePrintV2","iterationCount":125,"styleTransferAlgorithmType":"image","transferLearningEmbeddingType":"dynamic","handActionClassifierAugmentations":[]},"id":"B3CEB306-487A-4697-AFAA-9520516FA729"}